mcpmark/__init__.py
mcpmark/mcputils.py
mcpmark/cli/__init__.py
mcpmark/cli/check_one.py
mcpmark/cli/check_unpack.py
mcpmark/cli/cp_models.py
mcpmark/cli/echo_config.py
mcpmark/cli/export_marks.py
mcpmark/cli/extract_manual.py
mcpmark/cli/extract_plots.py
mcpmark/cli/find_duplicates.py
mcpmark/cli/grade_component.py
mcpmark/cli/grade_nbs.py
mcpmark/cli/grade_oknb.py
mcpmark/cli/make_feedback.py
mcpmark/cli/merge_marks.py
mcpmark/cli/mk_minimal_csv.py
mcpmark/cli/parse_manual_scores.py
mcpmark/cli/prepare_components.py
mcpmark/cli/rename_named_dirs.py
mcpmark/cli/run_notebooks.py
mcpmark/cli/scale_combine.py
mcpmark/tests/test_mcputils.py
mcpmark/tests/data/assign_config.yaml
mcpmark/tests/data/blank_comp_config.yaml
mcpmark/tests/data/empty_comp_config.yaml
mcpmark/tests/data/no_comp_config.yaml
mcpmark/tests/data/one_comp_config.yaml
mcpmark-0.1.dist-info/entry_points.txt
mcpmark-0.1.dist-info/LICENSE
mcpmark-0.1.dist-info/WHEEL
mcpmark-0.1.dist-info/METADATA
mcpmark-0.1.dist-info/RECORD
