Metadata-Version: 2.1
Name: mcpmark
Version: 0.1
Summary: Tools for grading multiple notebook component exercises.
Home-page: https://github.com/matthew-brett/mcpmark
Author: Matthew Brett
Author-email: matthew.brett@gmail.com
Requires-Python: >=3.6
Classifier: License :: OSI Approved :: BSD License
Classifier: Programming Language :: Python :: 3
Requires-Dist: gradools
Requires-Dist: rnbgrader>=0.2
